MixtureMetrics/MixtureMetrics.py
MixtureMetrics/__init__.py
MixtureMetrics-1.0.3.dist-info/LICENCE
MixtureMetrics-1.0.3.dist-info/METADATA
MixtureMetrics-1.0.3.dist-info/WHEEL
MixtureMetrics-1.0.3.dist-info/top_level.txt
MixtureMetrics-1.0.3.dist-info/RECORD
