Metadata-Version: 2.1
Name: MixtureMetrics
Version: 1.0.3
Summary: MixtureMetrics: A Comprehensive Package to Develop Additive Numerical Features to Describe Complex Materials for Machine Learning Modeling
Home-page: https://github.com/bakhras/MixtureDescriptors-I
Author: Rahel Mahini
Author-email: Rahil.Ashtarimahini@ndsu.edu
License: GPL-3.0
Classifier: Development Status :: 3 - Alpha
Classifier: Intended Audience :: Science/Research
Classifier: Topic :: Scientific/Engineering :: Chemistry
Classifier: License :: OSI Approved :: GNU General Public License v3 (GPLv3) 
Classifier: Programming Language :: Python :: 3.6
Requires-Python: >=3.6
License-File: LICENCE
Requires-Dist: numpy
Requires-Dist: pandas
